LICENSE
MANIFEST.in
README.rst
setup.py
numericalmodel/__init__.py
numericalmodel/equations.py
numericalmodel/genericmodel.py
numericalmodel/interfaces.py
numericalmodel/numericalmodel.py
numericalmodel/numericalschemes.py
numericalmodel/utils.py
numericalmodel.egg-info/PKG-INFO
numericalmodel.egg-info/SOURCES.txt
numericalmodel.egg-info/dependency_links.txt
numericalmodel.egg-info/requires.txt
numericalmodel.egg-info/top_level.txt
numericalmodel/examples/__init__.py
numericalmodel/examples/equations/__init__.py
numericalmodel/examples/equations/anemometer.py
numericalmodel/examples/equations/lineardecay.py
numericalmodel/examples/numericalmodel/__init__.py
numericalmodel/examples/numericalmodel/anemometer.py
numericalmodel/examples/numericalmodel/lineardecay.py
numericalmodel/ui/__init__.py
numericalmodel/ui/cli.py
numericalmodel/ui/plot.py
numericalmodel/ui/utils.py
numericalmodel/ui/gui/__init__.py
numericalmodel/ui/gui/gui.glade
numericalmodel/ui/gui/media/logo.png