Metadata-Version: 1.1
Name: numericalmodel
Version: 0.1.19
Summary: abstract classes to set up and run a numerical model
Home-page: https://gitlab.com/nobodyinperson/python3-numericalmodel
Author: Yann Büchau
Author-email: yann.buechau@web.de
License: GPLv3
Keywords: modelling
Platform: UNKNOWN
Classifier: License :: OSI Approved :: GNU General Public License v3 (GPLv3)
Classifier: Programming Language :: Python :: 3.5
Classifier: Operating System :: OS Independent
Classifier: Topic :: Software Development :: Libraries :: Python Modules
